{"100077":{"name":"DSP Bond Fund - Dividend","index":1},"100078":{"name":"DSP Bond Fund - Growth","index":1},"100079":{"name":"DSP Bond Fund - Monthly Dividend","index":1},"100080":{"name":"DSP Equity Fund - Regular Plan - Dividend","index":1},"100081":{"name":"DSP Equity & Bond Fund- Regular Plan - Growth","index":1},"100082":{"name":"DSP Equity & Bond Fund- Regular Plan -Dividend","index":1},"100084":{"name":"DSP Government Securities Fund - Regular Plan - Growth","index":1},"100085":{"name":"DSP Government Securities Fund - Regular Plan - Dividend","index":1},"100086":{"name":"DSP Government Securities Fund - Regular Plan - Monthly Dividend","index":1},"100087":{"name":"DSP Savings Fund - Regular Plan - Growth","index":1},"100088":{"name":"DSP Savings Fund - Regular Plan - Dividend","index":1},"100089":{"name":"DSP Savings Fund - Regular Plan - Monthly Dividend","index":1},"101303":{"name":"DSP Short Term Fund - Regular Plan - Regular Plan - Weekly Dividend","index":1},"101304":{"name":"DSP Short Term Fund - Regular Plan - Growth","index":1},"101305":{"name":"DSP Short Term Fund - Regular Plan - Dividend","index":1},"101306":{"name":"DSP Short Term Fund - Monthly Dividend","index":1},"101635":{"name":"DSP Top 100 Equity Fund - Regular Plan - Growth","index":1},"101636":{"name":"DSP Top 100 Equity Fund - Regular Plan - Dividend","index":1},"101837":{"name":"DSP Credit Risk Fund - Regular Plan -Growth","index":1},"101838":{"name":"DSP Credit Risk Fund - Regular Plan -Weekly Dividend","index":1},"101839":{"name":"DSP Credit Risk Fund - Regular Plan -Dividend","index":1},"101840":{"name":"DSP Credit Risk Fund - Regular Plan -Daily Dividend","index":1},"102434":{"name":"DSP India T.I.G.E.R. Fund - Regular Plan - Growth","index":1},"102435":{"name":"DSP India T.I.G.E.R. Fund - Regular Plan - Dividend","index":1},"102448":{"name":"DSP Regular Savings Fund- Regular Plan - Growth","index":1},"102450":{"name":"DSP Regular Savings Fund - Regular Plan - Monthly Dividend","index":1},"102451":{"name":"DSP Regular Savings Fund - Regular Plan - Quarterly Dividend","index":1},"103347":{"name":"DSP Liquidity Fund - Regular Plan - Growth","index":1},"103348":{"name":"DSP Liquidity Fund - Regular Plan - Weekly Dividend","index":1},"103349":{"name":"DSP Liquidity Fund- Regular Plan - Daily Dividend","index":1},"103819":{"name":"DSP Equity Opportunities Fund-Regular Plan - Growth","index":1},"103820":{"name":"DSP Equity Opportunities Fund-Regular Plan - Dividend","index":1},"104138":{"name":"DSP Ultra Short Fund - Regular Plan - Growth","index":1},"104139":{"name":"DSP Ultra Short Fund - Regular Plan - Weekly Dividend Reinvest","index":1},"104140":{"name":"DSP Ultra Short Fund - Regular Plan - Daily Dividend Reinvest","index":1},"104481":{"name":"DSP Midcap Fund - Regular Plan - Growth","index":1},"104482":{"name":"DSP Midcap Fund - Regular Plan - Dividend","index":1},"104772":{"name":"DSP Tax Saver Fund - Regular Plan - Growth","index":1},"104773":{"name":"DSP Tax Saver Fund - Regular Plan - Dividend","index":1},"105667":{"name":"DSP Strategic Bond Fund - Regular Plan - Monthly Dividend","index":1},"105668":{"name":"DSP Strategic Bond Fund - Regular Plan - Dividend","index":1},"105669":{"name":"DSP Strategic Bond Fund - Regular Plan - Growth","index":1},"105875":{"name":"DSP Equity Fund - Regular Plan - Growth","index":1},"105878":{"name":"DSP Strategic Bond Fund - Regular Plan - Weekly Dividend","index":1},"105989":{"name":"DSP Small Cap Fund - Regular - Growth","index":1},"106596":{"name":"DSP World Gold Fund - Regular Plan - Dividend","index":1},"106597":{"name":"DSP World Gold Fund - Regular Plan - Growth","index":1},"108202":{"name":"DSP Natural Resources And New Energy Fund - Regular - Growth","index":1},"108203":{"name":"DSP Natural Resources And New Energy Fund - Regular Plan - Dividend","index":1},"111786":{"name":"DSP Strategic Bond Fund - Regular Plan - Daily Dividend","index":1},"112126":{"name":"DSP World Energy Fund - Regular Plan - Growth","index":1},"112127":{"name":"DSP World Energy Fund - Regular Plan - Dividend","index":1},"112293":{"name":"DSP World Mining Fund - Regular Plan - Growth","index":1},"112347":{"name":"DSP World Mining Fund - Regular Plan - Dividend","index":1},"112901":{"name":"DSP Focus Fund - Regular Plan - Growth","index":1},"113032":{"name":"DSP Focus Fund - Regular Plan - Dividend","index":1},"113153":{"name":"DSP Small Cap Fund - Regular - Dividend","index":1},"115881":{"name":"DSP World Agriculture Fund - Regular Plan - Dividend","index":1},"115882":{"name":"DSP World Agriculture Fund - Regular Plan - Growth","index":1},"117061":{"name":"DSP Credit Risk Fund - Regular Plan - Monthly Dividend","index":1},"117062":{"name":"DSP Credit Risk Fund - Regular Plan - Quarterly Dividend","index":1},"117063":{"name":"DSP Ultra Short Fund - Regular Plan - Monthly Dividend","index":1},"117691":{"name":"DSP US Flexible Equity Fund - Regular Plan - Growth Option","index":1},"117692":{"name":"DSP US Flexible Equity Fund - Regular Plan - Dividend Option","index":1},"117995":{"name":"DSP Ultra Short Fund - Regular Plan - Dividend Payout","index":1},"118921":{"name":"DSP Bond Fund - Direct Plan - Monthly Dividend","index":1},"118922":{"name":"DSP Bond Fund - Direct Plan - Dividend","index":1},"118924":{"name":"DSP Bond Fund - Direct Plan - Growth","index":1},"118992":{"name":"DSP Regular Savings Fund - Direct Plan - Monthly Dividend","index":1},"118993":{"name":"DSP Regular Savings Fund - Direct Plan - Quarterly Dividend","index":1},"118994":{"name":"DSP Regular Savings Fund - Direct Plan - Growth","index":1},"119019":{"name":"DSP Equity & Bond Fund - Direct Plan - Growth","index":1},"119020":{"name":"DSP Equity & Bond Fund - Direct Plan - Dividend","index":1},"119028":{"name":"DSP Natural Resources and New Energy Fund - Direct Plan - Growth","index":1},"119029":{"name":"DSP Natural Resources and New Energy Fund - Direct Plan - Dividend","index":1},"119070":{"name":"DSP Midcap Fund - Direct Plan - Dividend","index":1},"119071":{"name":"DSP Midcap Fund - Direct Plan - Growth","index":1},"119076":{"name":"DSP Equity Fund - Direct Plan - Growth","index":1},"119077":{"name":"DSP Equity Fund - Direct Plan - Dividend","index":1},"119082":{"name":"DSP Credit Risk Fund - Direct Plan - Growth","index":1},"119083":{"name":"DSP Credit Risk Fund - Direct Plan - Dividend","index":1},"119084":{"name":"DSP Credit Risk Fund - Direct Plan - Monthly Dividend","index":1},"119085":{"name":"DSP Credit Risk Fund - Direct Plan - Quarterly Dividend","index":1},"119086":{"name":"DSP Credit Risk Fund - Direct Plan - Weekly Dividend","index":1},"119087":{"name":"DSP Credit Risk Fund - Direct Plan - Daily Dividend","index":1},"119095":{"name":"DSP Focus Fund - Direct Plan - Dividend","index":1},"119096":{"name":"DSP Focus Fund - Direct Plan - Growth","index":1},"119099":{"name":"DSP Government Securities Fund - Direct Plan - Growth","index":1},"119100":{"name":"DSP Government Securities Fund - Direct Plan - Monthly Dividend","index":1},"119101":{"name":"DSP Government Securities Fund - Direct Plan - Dividend","index":1},"119106":{"name":"DSP Savings Fund - Direct Plan - Growth","index":1},"119107":{"name":"DSP Savings Fund - Direct Plan - Monthly Dividend","index":1},"119108":{"name":"DSP Savings Fund - Direct Plan - Dividend","index":1},"119123":{"name":"DSP Liquidity Fund - Direct Plan - Weekly Dividend","index":1},"119124":{"name":"DSP Liquidity Fund - Direct Plan - Daily Dividend","index":1},"119125":{"name":"DSP Liquidity Fund - Direct Plan - Growth","index":1},"119203":{"name":"DSP Ultra Short Fund - Direct Plan - Daily Dividend","index":1},"119204":{"name":"DSP Ultra Short Fund - Direct Plan - Monthly Dividend","index":1},"119205":{"name":"DSP Ultra Short Fund - Direct Plan - Growth","index":1},"119206":{"name":"DSP Ultra Short Fund - Direct Plan - Dividend","index":1},"119207":{"name":"DSP Ultra Short Fund - Direct Plan - Weekly Dividend","index":1},"119212":{"name":"DSP Small Cap Fund - Direct Plan - Growth","index":1},"119213":{"name":"DSP Small Cap Fund - Direct Plan - Dividend","index":1},"119218":{"name":"DSP Equity Opportunities Fund - Direct Plan - Growth","index":1},"119219":{"name":"DSP Equity Opportunities Fund - Direct Plan - Dividend","index":1},"119222":{"name":"DSP Short Term Fund - Direct Plan - Dividend","index":1},"119223":{"name":"DSP Short Term Fund - Direct Plan - Weekly Dividend","index":1},"119224":{"name":"DSP Short Term Fund - Direct Plan - Monthly Dividend","index":1},"119226":{"name":"DSP Short Term Fund - Direct Plan - Growth","index":1},"119236":{"name":"DSP Strategic Bond Fund - Direct Plan - Monthly Dividend","index":1},"119237":{"name":"DSP Strategic Bond Fund - Direct Plan - Weekly Dividend","index":1},"119238":{"name":"DSP Strategic Bond Fund - Direct Plan - Dividend","index":1},"119239":{"name":"DSP Strategic Bond Fund - Direct Plan - Growth","index":1},"119240":{"name":"DSP Strategic Bond Fund - Direct Plan - Daily Dividend","index":1},"119241":{"name":"DSP Tax Saver Fund - Direct Plan - Dividend","index":1},"119242":{"name":"DSP Tax Saver Fund - Direct Plan - Growth","index":1},"119247":{"name":"DSP India T.I.G.E.R. Fund - Direct Plan - Growth","index":1},"119248":{"name":"DSP India T.I.G.E.R. Fund - Direct Plan - Dividend","index":1},"119249":{"name":"DSP Top 100 Equity Fund - Direct Plan - Dividend","index":1},"119250":{"name":"DSP Top 100 Equity Fund - Direct Plan - Growth","index":1},"119252":{"name":"DSP US Flexible Equity Fund - Direct Plan - Growth","index":1},"119253":{"name":"DSP US Flexible Equity Fund - Direct Plan - Dividend","index":1},"119271":{"name":"DSP World Agriculture Fund - Direct Plan - Growth","index":1},"119272":{"name":"DSP World Agriculture Fund - Direct Plan - Dividend","index":1},"119275":{"name":"DSP World Energy Fund - Direct Plan - Growth","index":1},"119276":{"name":"DSP World Energy Fund - Direct Plan - Dividend","index":1},"119277":{"name":"DSP World Gold Fund - Direct Plan - Growth","index":1},"119278":{"name":"DSP World Gold Fund - Direct Plan - Dividend","index":1},"119279":{"name":"DSP World Mining Fund - Direct Plan - Growth","index":1},"119280":{"name":"DSP World Mining Fund - Direct Plan - Dividend","index":1},"123287":{"name":"DSP Savings Fund - Regular Plan - Daily Dividend","index":1},"123288":{"name":"DSP Savings Fund - Direct Plan - Daily Dividend","index":1},"124172":{"name":"DSP Banking & PSU Debt Fund - Regular Plan - Growth","index":1},"124173":{"name":"DSP Banking & PSU Debt Fund - Regular Plan - Daily Dividend Reinvest","index":1},"124174":{"name":"DSP Banking & PSU Debt Fund - Regular Plan - Dividend Payout & Reinvest","index":1},"124175":{"name":"DSP Banking & PSU Debt Fund - Direct Plan - Growth","index":1},"124176":{"name":"DSP Banking & PSU Debt Fund - Direct Plan - Monthly Dividend Payout & Reinvest","index":1},"124177":{"name":"DSP Banking & PSU Debt Fund - Direct Plan - Quarterly Dividend Payout & Reinvest","index":1},"124178":{"name":"DSP Banking & PSU Debt Fund - Direct Plan - Dividend Payout & Reinvest","index":1},"124179":{"name":"DSP Banking & PSU Debt Fund - Regular Plan - Weekly Dividend Payout & Reinvest","index":1},"124180":{"name":"DSP Banking & PSU Debt Fund - Regular Plan - Monthly Dividend Payout & Reinvest","index":1},"124181":{"name":"DSP Banking & PSU Debt Fund - Regular Plan - Quarterly Dividend Payout & Reinvest","index":1},"124182":{"name":"DSP Banking & PSU Debt Fund - Direct Plan - Daily Dividend Reinvest","index":1},"124183":{"name":"DSP Banking & PSU Debt Fund - Direct Plan - Weekly Dividend Payout & Reinvest","index":1},"126391":{"name":"DSP Dynamic Asset Allocation Fund - Direct Plan - Monthly Dividend","index":1},"126392":{"name":"DSP Dynamic Asset Allocation Fund - Regular Plan - Monthly Dividend","index":1},"126393":{"name":"DSP Dynamic Asset Allocation Fund - Direct Plan - Growth","index":1},"126394":{"name":"DSP Dynamic Asset Allocation Fund - Regular Plan - Growth","index":1},"130490":{"name":"DSP Global Allocation Fund - Regular Plan - Dividend","index":1},"130491":{"name":"DSP Global Allocation Fund - Direct Plan - Dividend","index":1},"130492":{"name":"DSP Global Allocation Fund - Regular Plan - Growth","index":1},"130493":{"name":"DSP Global Allocation Fund - Direct Plan - Growth","index":1},"131297":{"name":"DSP 10Y G-Sec Fund - Regular Plan - Growth","index":1},"131298":{"name":"DSP 10Y G-Sec Fund - Regular Plan - Dividend","index":1},"131299":{"name":"DSP 10Y G-Sec Fund - Regular Plan - Monthly Dividend","index":1},"131300":{"name":"DSP 10Y G-Sec Fund - Regular Plan - Quarterly Dividend","index":1},"131301":{"name":"DSP 10Y G-Sec Fund - Direct Plan - Growth","index":1},"131302":{"name":"DSP 10Y G-Sec Fund - Direct Plan - Quarterly Dividend","index":1},"131303":{"name":"DSP 10Y G-Sec Fund - Direct Plan - Monthly Dividend","index":1},"131304":{"name":"DSP 10Y G-Sec Fund - Direct Plan - Dividend","index":1},"131482":{"name":"DSP 3 Years Close Ended Equity Fund - Regular Plan - Growth (Maturity Date 4-Jan-2021)","index":1},"131483":{"name":"DSP 3 Years Close Ended Equity Fund - Direct Plan - Dividend (Maturity Date 4-Jan-2021)","index":1},"131484":{"name":"DSP 3 Years Close Ended Equity Fund - Direct Plan - Growth (Maturity Date 4-Jan-2021)","index":1},"131485":{"name":"DSP 3 Years Close Ended Equity Fund - Regular Plan - Dividend (Maturity Date 4-Jan-2021)","index":1},"133919":{"name":"DSP Low Duration Fund - Regular Plan - Daily Dividend","index":1},"133920":{"name":"DSP Low Duration Fund - Regular Plan - Monthly Dividend","index":1},"133921":{"name":"DSP Low Duration Fund - Regular Plan - Quarterly Dividend","index":1},"133922":{"name":"DSP Low Duration Fund - Direct Plan - Daily Dividend","index":1},"133923":{"name":"DSP Low Duration Fund - Direct Plan - Weekly Dividend","index":1},"133924":{"name":"DSP Low Duration Fund - Direct Plan - Quarterly Dividend","index":1},"133925":{"name":"DSP Low Duration Fund - Direct Plan - Growth","index":1},"133926":{"name":"DSP Low Duration Fund - Regular Plan - Growth","index":1},"133927":{"name":"DSP Low Duration Fund - Regular Plan - Weekly Dividend","index":1},"133928":{"name":"DSP Low Duration Fund - Direct Plan - Monthly Dividend","index":1},"136563":{"name":"DSP Equity Savings Fund - Regular Plan - Growth","index":1},"136564":{"name":"DSP Equity Savings Fund - Regular Plan - Dividend","index":1},"136565":{"name":"DSP Equity Savings Fund - Regular Plan - Monthly Dividend","index":1},"136566":{"name":"DSP Equity Savings Fund - Regular Plan - Quarterly Dividend","index":1},"136567":{"name":"DSP Equity Savings Fund - Direct Plan - Growth","index":1},"136568":{"name":"DSP Equity Savings Fund - Direct Plan - Dividend","index":1},"136569":{"name":"DSP Equity Savings Fund - Direct Plan - Monthly Dividend","index":1},"136570":{"name":"DSP Equity Savings Fund - Direct Plan - Quarterly Dividend","index":1},"139303":{"name":"DSP Savings Fund - Unclaimed Redemption - Upto 3 years","index":1},"139304":{"name":"DSP Savings Fund - Unclaimed Redemption - Beyond 3 years","index":1},"139305":{"name":"DSP Savings Fund - Unclaimed Dividend - Upto 3 years","index":1},"139306":{"name":"DSP Savings Fund - Unclaimed Dividend - Beyond 3 years","index":1},"140061":{"name":"DSP Dual Advantage Fund - Series 49 - 42M - Regular - Dividend Payout","index":1},"140062":{"name":"DSP Dual Advantage Fund - Series 49 - 42M - Regular - Growth","index":1},"140063":{"name":"DSP Dual Advantage Fund - Series 49 - 42M - Direct - Growth","index":1},"140829":{"name":"DSP FMP - Series 204 - 37M - Regular Plan - Dividend - Regular Payout","index":1},"140831":{"name":"DSP FMP - Series 204 - 37M - Regular Plan - Growth","index":1},"140832":{"name":"DSP FMP - Series 204 - 37M - Regular Plan - Dividend - Quarterly Payout","index":1},"140833":{"name":"DSP FMP - Series 204 - 37M - Direct Plan - Growth","index":1},"140834":{"name":"DSP FMP - Series 204 - 37M - Direct Plan - Dividend - Regular Payout","index":1},"141018":{"name":"DSP FMP - Series 205 - 37M - Regular Plan - Growth","index":1},"141020":{"name":"DSP FMP - Series 205 - 37M - Regular Plan - Dividend - Quarterly Payout","index":1},"141021":{"name":"DSP FMP - Series 205 - 37M - Direct Plan - Growth","index":1},"141022":{"name":"DSP FMP - Series 205 - 37M - Direct Plan - Dividend - Regular Payout","index":1},"141101":{"name":"DSP FMP - Series 209 -37M - Regular Plan - Growth","index":1},"141102":{"name":"DSP FMP - Series 209 - 37M - Regular Plan - Dividend - Regular Payout","index":1},"141103":{"name":"DSP FMP - Series 209 - 37M - Direct Plan - Dividend - Regular Payout","index":1},"141104":{"name":"DSP FMP - Series 209 - 37M - Direct Plan - Growth","index":1},"141105":{"name":"DSP FMP - Series 209 - 37M - Regular Plan - Dividend - Quarterly Payout","index":1},"141106":{"name":"DSP FMP - Series 209 - 37M - Direct Plan - Dividend - Quarterly Payout","index":1},"141211":{"name":"DSP FMP - Series 210 - 36M - Regular Plan - Dividend - Regular Payout","index":1},"141212":{"name":"DSP FMP - Series 210 - 36M - Direct Plan - Dividend - Quarterly Payout","index":1},"141213":{"name":"DSP FMP - Series 210 - 36M - Direct Plan - Dividend - Regular Payout","index":1},"141214":{"name":"DSP FMP - Series 210 - 36M - Regular Plan - Growth","index":1},"141215":{"name":"DSP FMP - Series 210 - 36M - Direct Plan - Growth","index":1},"141216":{"name":"DSP FMP - Series 210 - 36M - Regular Plan - Dividend - Quarterly Payout","index":1},"141317":{"name":"DSP FMP - Series 211 - 38M - Direct Plan - Growth","index":1},"141318":{"name":"DSP FMP - Series 211 - 38M - Regular Plan - Growth","index":1},"141319":{"name":"DSP FMP - Series 211 - 38M - Regular Plan - Dividend - Regular Payout","index":1},"141320":{"name":"DSP FMP - Series 211 - 38M - Direct Plan - Dividend - Regular Payout","index":1},"141321":{"name":"DSP FMP - Series 211 - 38M - Direct Plan - Dividend - Quarterly Payout","index":1},"141322":{"name":"DSP FMP - Series 211 - 38M - Regular Plan - Dividend - Quarterly Payout","index":1},"141875":{"name":"DSP Equal Nifty 50 Fund - Regular Plan - Growth","index":1},"141876":{"name":"DSP Equal Nifty 50 Fund - Regular Plan - Dividend","index":1},"141877":{"name":"DSP Equal Nifty 50 Fund - Direct Plan - Growth","index":1},"141878":{"name":"DSP Equal Nifty 50 Fund - Direct Plan - Dividend","index":1},"141969":{"name":"DSP A.C.E. Fund (Analyst's Conviction Equalized) - Series 1 - Regular Plan - Growth","index":1},"141970":{"name":"DSP A.C.E. Fund (Analyst's Conviction Equalized) - Series 1 - Regular Plan - Dividend Payout","index":1},"141971":{"name":"DSP A.C.E. Fund (Analyst's Conviction Equalized) - Series 1 - Direct Plan - Growth","index":1},"141972":{"name":"DSP A.C.E. Fund (Analyst's Conviction Equalized) - Series 1 - Direct Plan - Dividend Payout","index":1},"142163":{"name":"DSP FMP Series - 217 - 40M - Regular Plan - Dividend Payout","index":1},"142164":{"name":"DSP FMP Series - 217 - 40M - Direct Plan - Growth","index":1},"142165":{"name":"DSP FMP Series - 217 - 40M - Direct Plan - Dividend Payout","index":1},"142166":{"name":"DSP FMP Series - 217 - 40M - Direct Plan - Dividend Quarterly Payout","index":1},"142167":{"name":"DSP FMP Series - 217 - 40M - Regular Plan - Growth","index":1},"142168":{"name":"DSP FMP Series - 217 - 40M - Regular Plan - Dividend Quarterly Payout","index":1},"142250":{"name":"DSP FMP Series - 218 - 40M - Regular Plan - Dividend Quarterly Payout","index":1},"142251":{"name":"DSP FMP Series - 218 - 40M - Regular Plan - Dividend Payout","index":1},"142252":{"name":"DSP FMP Series - 218 - 40M - Regular Plan - Growth","index":1},"142253":{"name":"DSP FMP Series - 218 - 40M - Direct Plan - Dividend Quarterly Payout","index":1},"142254":{"name":"DSP FMP Series - 218 - 40M - Direct Plan - Growth","index":1},"142255":{"name":"DSP FMP Series - 218 - 40M - Direct Plan - Dividend Payout","index":1},"142278":{"name":"DSP Arbitrage Fund - Regular - Monthly Dividend","index":1},"142279":{"name":"DSP Arbitrage Fund - Direct - Dividend","index":1},"142280":{"name":"DSP Arbitrage Fund - Regular - Dividend","index":1},"142281":{"name":"DSP Arbitrage Fund - Direct - Monthly Dividend","index":1},"142282":{"name":"DSP Arbitrage Fund - Regular - Growth","index":1},"142283":{"name":"DSP Arbitrage Fund - Direct - Growth","index":1},"142306":{"name":"DSP FMP Series - 219 - 40M - Regular Plan - Growth","index":1},"142307":{"name":"DSP FMP Series - 219 - 40M - Regular Plan - Dividend Payout","index":1},"142308":{"name":"DSP FMP Series - 219 - 40M - Regular Plan - Dividend Quarterly Payout","index":1},"142309":{"name":"DSP FMP Series - 219 - 40M - Direct Plan - Growth","index":1},"142310":{"name":"DSP FMP Series - 219 - 40M - Direct Plan - Dividend Payout","index":1},"142311":{"name":"DSP FMP Series - 219 - 40M - Direct Plan - Dividend Quarterly Payout","index":1},"142471":{"name":"DSP FMP Series - 220 - 40M - Regular Plan - Growth","index":1},"142472":{"name":"DSP FMP Series - 220 - 40M - Regular Plan - Dividend Payout","index":1},"142474":{"name":"DSP FMP Series - 220 - 40M - Regular Plan - Dividend Quarterly Payout","index":1},"142475":{"name":"DSP FMP Series - 220 - 40M - Direct Plan - Growth","index":1},"142497":{"name":"DSP A.C.E. Fund (Analyst's Conviction Equalized) - Series 2 - Direct Plan - Dividend Payout","index":1},"142498":{"name":"DSP A.C.E. Fund (Analyst's Conviction Equalized) - Series 2 - Regular Plan - Growth","index":1},"142499":{"name":"DSP A.C.E. Fund (Analyst's Conviction Equalized) - Series 2 - Direct Plan - Growth","index":1},"142500":{"name":"DSP A.C.E. Fund (Analyst's Conviction Equalized) - Series 2 - Regular Plan - Dividend Payout","index":1},"142501":{"name":"DSP FMP Series - 221 - 40M - Regular Plan - Growth","index":1},"142502":{"name":"DSP FMP Series - 221 - 40M - Regular Plan - Dividend Payout","index":1},"142503":{"name":"DSP FMP Series - 221 - 40M - Regular Plan - Dividend Quarterly Payout","index":1},"142504":{"name":"DSP FMP Series - 221 - 40M - Direct Plan - Growth","index":1},"142505":{"name":"DSP FMP Series - 221 - 40M - Direct Plan - Dividend Quarterly Payout","index":1},"142506":{"name":"DSP FMP Series - 221 - 40M - Direct Plan - Dividend Payout","index":1},"142589":{"name":"DSP Liquid ETF - Daily Dividend Reinvest","index":1},"142783":{"name":"DSP FMP Series - 223 - 39M - Regular Plan - Growth","index":1},"142784":{"name":"DSP FMP Series - 223 - 39M - Regular Plan - Dividend Quarterly Payout","index":1},"142785":{"name":"DSP FMP Series - 223 - 39M - Regular Plan - Dividend Payout","index":1},"142786":{"name":"DSP FMP Series - 223 - 39M - Direct Plan - Dividend Payout","index":1},"142788":{"name":"DSP FMP Series - 223 - 39M - Direct Plan - Growth","index":1},"142834":{"name":"DSP FMP Series - 224 - 39M - Regular Plan - Growth","index":1},"142835":{"name":"DSP FMP Series - 224 - 39M - Regular Plan - Dividend Payout","index":1},"142836":{"name":"DSP FMP Series - 224 - 39M - Regular Plan - Dividend Quarterly Payout","index":1},"142837":{"name":"DSP FMP Series - 224 - 39M - Direct Plan - Growth","index":1},"142839":{"name":"DSP FMP Series - 224 - 39M - Direct Plan - Dividend Quarterly Payout","index":1},"142935":{"name":"DSP FMP Series - 226 - 39M - Regular Plan - Dividend Payout","index":1},"142936":{"name":"DSP FMP Series - 226 - 39M - Regular Plan - Dividend Quarterly Payout","index":1},"142937":{"name":"DSP FMP Series - 226 - 39M - Direct Plan - Dividend Quarterly Payout","index":1},"142938":{"name":"DSP FMP Series - 226 - 39M - Regular Plan - Growth","index":1},"142939":{"name":"DSP FMP Series - 226 - 39M - Direct Plan - Growth","index":1},"143033":{"name":"DSP FMP Series - 227 - 39M - Regular Plan - Dividend Payout","index":1},"143034":{"name":"DSP FMP Series - 227 - 39M - Regular Plan - Dividend Quarterly Payout","index":1},"143036":{"name":"DSP FMP Series - 227 - 39M - Regular Plan - Growth","index":1},"143037":{"name":"DSP FMP Series - 227 - 39M - Direct Plan - Growth","index":1},"143038":{"name":"DSP FMP Series - 227 - 39M - Direct Plan - Dividend Payout","index":1},"143696":{"name":"DSP FMP Series - 232 - 36M - Direct Plan - Growth","index":1},"143697":{"name":"DSP FMP Series - 232 - 36M - Direct Plan - Dividend Payout","index":1},"143698":{"name":"DSP FMP Series - 232 - 36M - Regular Plan - Dividend Payout","index":1},"143700":{"name":"DSP FMP Series - 232 - 36M - Regular Plan - Growth","index":1},"143851":{"name":"DSP FMP Series - 233 - 36M - Regular Plan - Growth","index":1},"143852":{"name":"DSP FMP Series - 233 - 36M - Regular Plan - Dividend Payout","index":1},"143853":{"name":"DSP FMP Series - 233 - 36M - Regular Plan - Dividend Quarterly Payout","index":1},"143854":{"name":"DSP FMP Series - 233 - 36M - Direct Plan - Growth","index":1},"143939":{"name":"DSP FMP Series - 235 - 36M - Regular Plan - Dividend Payout","index":1},"143940":{"name":"DSP FMP Series - 235 - 36M - Direct Plan - Growth","index":1},"143943":{"name":"DSP FMP Series - 235 - 36M - Regular Plan - Growth","index":1},"143944":{"name":"DSP FMP Series - 235 - 36M - Regular Plan - Dividend Quarterly Payout","index":1},"144119":{"name":"DSP FMP Series - 236 - 36M - Direct Plan - Growth","index":1},"144120":{"name":"DSP FMP Series - 236 - 36M - Direct Plan - Dividend Payout","index":1},"144122":{"name":"DSP FMP Series - 236 - 36M - Regular Plan - Dividend Payout","index":1},"144123":{"name":"DSP FMP Series - 236 - 36M - Regular Plan - Dividend Quarterly Payout","index":1},"144124":{"name":"DSP FMP Series - 236 - 36M - Regular Plan - Growth","index":1},"144215":{"name":"DSP FMP Series - 237 - 36M - Direct Plan - Growth","index":1},"144217":{"name":"DSP FMP Series - 237 - 36M - Regular Plan - Dividend Quarterly Payout","index":1},"144218":{"name":"DSP FMP Series - 237 - 36M - Direct Plan - Dividend Quarterly Payout","index":1},"144219":{"name":"DSP FMP Series - 237 - 36M - Regular Plan - Dividend Payout","index":1},"144220":{"name":"DSP FMP Series - 237 - 36M - Regular Plan - Growth","index":1},"144241":{"name":"DSP FMP Series - 238 - 36M - Regular Plan - Growth","index":1},"144242":{"name":"DSP FMP Series - 238 - 36M - Regular Plan - Dividend Quarterly Payout","index":1},"144243":{"name":"DSP FMP Series - 238 - 36M - Direct Plan - Growth","index":1},"144245":{"name":"DSP FMP Series - 238 - 36M - Regular Plan - Dividend Payout","index":1},"144246":{"name":"DSP FMP Series - 238 - 36M - Direct Plan - Dividend Payout","index":1},"144295":{"name":"DSP FMP Series - 239 - 36M - Regular Plan - Growth","index":1},"144296":{"name":"DSP FMP Series - 239 - 36M - Regular Plan - Dividend Payout","index":1},"144299":{"name":"DSP FMP Series - 239 - 36M - Direct Plan - Growth","index":1},"144516":{"name":"DSP FMP Series - 241 - 36M - Regular Plan - Growth","index":1},"144517":{"name":"DSP FMP Series - 241 - 36M - Direct Plan - Dividend Quarterly Payout","index":1},"144518":{"name":"DSP FMP Series - 241 - 36M - Regular Plan - Dividend Payout","index":1},"144519":{"name":"DSP FMP Series - 241 - 36M - Regular Plan - Dividend Quarterly Payout","index":1},"144520":{"name":"DSP FMP Series - 241 - 36M - Direct Plan - Growth","index":1},"144628":{"name":"DSP FMP Series - 243 - 36M - Regular Plan - Growth","index":1},"144629":{"name":"DSP FMP Series - 243 - 36M - Regular Plan - Dividend Payout","index":1},"144630":{"name":"DSP FMP Series - 243 - 36M - Regular Plan - Dividend Quarterly Payout","index":1},"144631":{"name":"DSP FMP Series - 243 - 36M - Direct Plan - Dividend Payout","index":1},"144632":{"name":"DSP FMP Series - 243 - 36M - Direct Plan - Dividend Quarterly Payout","index":1},"144633":{"name":"DSP FMP Series - 243 - 36M - Direct Plan - Growth","index":1},"144644":{"name":"DSP Corporate Bond Fund - Regular - Growth","index":1},"144645":{"name":"DSP Corporate Bond Fund - Regular - Monthly Dividend","index":1},"144646":{"name":"DSP Corporate Bond Fund - Direct - Growth","index":1},"144647":{"name":"DSP Corporate Bond Fund - Direct - Dividend","index":1},"144648":{"name":"DSP Corporate Bond Fund - Direct - Quarterly Dividend","index":1},"144649":{"name":"DSP Corporate Bond Fund - Regular - Quarterly Dividend","index":1},"144650":{"name":"DSP Corporate Bond Fund - Regular - Dividend","index":1},"144651":{"name":"DSP Corporate Bond Fund - Direct - Monthly Dividend","index":1},"144820":{"name":"DSP FMP Series - 244 - 36M - Regular Plan - Growth","index":1},"144822":{"name":"DSP FMP Series - 244 - 36M - Regular Plan - Dividend Quarterly Payout","index":1},"144823":{"name":"DSP FMP Series - 244 - 36M - Direct Plan - Growth","index":1},"144824":{"name":"DSP FMP Series - 244 - 36M - Direct Plan - Dividend Payout","index":1},"144825":{"name":"DSP FMP Series - 244 - 36M - Direct Plan - Dividend Quarterly Payout","index":1},"145453":{"name":"DSP Healthcare Fund - Regular Plan - Dividend","index":1},"145454":{"name":"DSP Healthcare Fund - Direct Plan - Growth","index":1},"145455":{"name":"DSP Healthcare Fund - Direct Plan - Dividend","index":1},"145456":{"name":"DSP Healthcare Fund - Regular Plan - Growth","index":1},"146061":{"name":"DSP Overnight Fund - Regular Plan - Growth","index":1},"146062":{"name":"DSP Overnight Fund - Direct Plan - Growth","index":1},"146063":{"name":"DSP Overnight Fund - Regular Plan - Weekly Dividend","index":1},"146064":{"name":"DSP Overnight Fund - Direct Plan - Weekly Dividend","index":1},"146065":{"name":"DSP Overnight Fund - Direct Plan - Daily Dividend","index":1},"146066":{"name":"DSP Overnight Fund - Regular Plan - Daily Dividend","index":1},"146376":{"name":"DSP Nifty 50 Index Fund - Direct Plan - Growth","index":1},"146377":{"name":"DSP Nifty 50 Index Fund - Direct Plan - Dividend","index":1},"146378":{"name":"DSP Nifty 50 Index Fund - Regular Plan - Dividend","index":1},"146379":{"name":"DSP Nifty 50 Index Fund - Regular Plan - Growth","index":1},"146380":{"name":"DSP Nifty Next 50 Index Fund - Regular Plan - Growth","index":1},"146381":{"name":"DSP Nifty Next 50 Index Fund - Direct Plan - Growth","index":1},"146382":{"name":"DSP Nifty Next 50 Index Fund - Direct Plan - Dividend","index":1},"146383":{"name":"DSP Nifty Next 50 Index Fund - Regular Plan - Dividend","index":1},"146459":{"name":"DSP FMP Series - 250 - 39M - Regular Plan - Growth","index":1},"146460":{"name":"DSP FMP Series - 250 - 39M - Regular Plan - Dividend Payout","index":1},"146461":{"name":"DSP FMP Series - 250 - 39M - Regular Plan - Dividend Quarterly Payout","index":1},"146462":{"name":"DSP FMP Series - 250 - 39M - Direct Plan - Growth","index":1},"146463":{"name":"DSP FMP Series - 250 - 39M - Direct Plan - Dividend Payout","index":1},"146464":{"name":"DSP FMP Series - 250 - 39M - Direct Plan - Dividend Quarterly Payout","index":1},"146739":{"name":"DSP FMP Series - 251 - 38M - Regular Plan - Dividend Payout","index":1},"146740":{"name":"DSP FMP Series - 251 - 38M - Regular Plan - Dividend Quarterly Payout","index":1},"146741":{"name":"DSP FMP Series - 251 - 38M - Direct Plan - Growth","index":1},"146742":{"name":"DSP FMP Series - 251 - 38M - Direct Plan - Dividend Payout","index":1},"146744":{"name":"DSP FMP Series - 251 - 38M - Regular Plan - Growth","index":1},"147303":{"name":"DSP Quant Fund - Regular Plan - Growth","index":1},"147304":{"name":"DSP Quant Fund - Direct Plan - Dividend","index":1},"147305":{"name":"DSP Quant Fund - Regular Plan - Dividend","index":1},"147306":{"name":"DSP Quant Fund - Direct Plan - Growth","index":1}}